anytype/__init__.py
anytype/anytype.py
anytype/api.py
anytype/apimodels.py
anytype/block.py
anytype/constants.py
anytype/list.py
anytype/member.py
anytype/object.py
anytype/property.py
anytype/space.py
anytype/tag.py
anytype/template.py
anytype/type.py
anytype/utils.py
anytype/view.py
anytype_pyclient-0.0.6.dist-info/licenses/LICENSE
anytype_pyclient-0.0.6.dist-info/METADATA
anytype_pyclient-0.0.6.dist-info/WHEEL
anytype_pyclient-0.0.6.dist-info/top_level.txt
anytype_pyclient-0.0.6.dist-info/RECORD
