Metadata-Version: 2.4
Name: anytype-pyclient
Version: 0.0.6
Summary: python client for anytype api.
Author-email: a-bite-of-code <jie.mei1@qq.com>
License: MIT
Project-URL: Source Code, https://github.com/a-bite-of-code/anytype-pyclient
Classifier: Programming Language :: Python :: 3
Classifier: License :: OSI Approved :: MIT License
Requires-Python: >=3.13
License-File: LICENSE
Requires-Dist: requests
Requires-Dist: pydantic
Requires-Dist: python-dotenv
Dynamic: license-file
